pdf4llm/__init__.py
pdf4llm-0.2.7.dist-info/licenses/LICENSE
pdf4llm-0.2.7.dist-info/METADATA
pdf4llm-0.2.7.dist-info/WHEEL
pdf4llm-0.2.7.dist-info/top_level.txt
pdf4llm-0.2.7.dist-info/RECORD
