Metadata-Version: 2.4
Name: pdf4llm
Version: 0.2.7
Summary: PyMuPDF Utilities for LLM/RAG
Home-page: https://github.com/pymupdf/RAG
Author: Artifex
Author-email: support@artifex.com
License: Dual Licensed - GNU AFFERO GPL 3.0 or Artifex Commercial License
Project-URL: Documentation, https://pymupdf.readthedocs.io/
Project-URL: Source, https://github.com/pymupdf/RAG/tree/main/pdf4llm/pdf4llm
Project-URL: Tracker, https://github.com/pymupdf/RAG/issues
Project-URL: Changelog, https://github.com/pymupdf/RAG/blob/main/CHANGES.md
Project-URL: License, https://github.com/pymupdf/RAG/blob/main/LICENSE
Classifier: Development Status :: 5 - Production/Stable
Classifier: Environment :: Console
Classifier: Intended Audience :: Developers
Classifier: Programming Language :: Python :: 3
Classifier: Topic :: Utilities
Requires-Python: >=3.10
License-File: LICENSE
Requires-Dist: pymupdf4llm==0.2.7
Dynamic: author
Dynamic: author-email
Dynamic: classifier
Dynamic: description
Dynamic: description-content-type
Dynamic: home-page
Dynamic: license
Dynamic: license-file
Dynamic: project-url
Dynamic: requires-dist
Dynamic: requires-python
Dynamic: summary
